scribe_data/__init__.py
scribe_data/utils.py
scribe_data/check/check_project_metadata.py
scribe_data/check/check_project_structure.py
scribe_data/check/check_pyicu.py
scribe_data/check/check_query_forms.py
scribe_data/check/check_query_identifiers.py
scribe_data/cli/__init__.py
scribe_data/cli/cli_utils.py
scribe_data/cli/convert.py
scribe_data/cli/get.py
scribe_data/cli/interactive.py
scribe_data/cli/list.py
scribe_data/cli/main.py
scribe_data/cli/total.py
scribe_data/cli/upgrade.py
scribe_data/cli/version.py
scribe_data/load/__init__.py
scribe_data/load/data_to_sqlite.py
scribe_data/load/send_dbs_to_scribe.py
scribe_data/resources/__init__.py
scribe_data/resources/data_type_metadata.json
scribe_data/resources/language_metadata.json
scribe_data/resources/lexeme_form_metadata.json
scribe_data/unicode/2021_ranked.tsv
scribe_data/unicode/UNICODE_INSTALLTION.md
scribe_data/unicode/__init__.py
scribe_data/unicode/generate_emoji_keywords.py
scribe_data/unicode/process_unicode.py
scribe_data/unicode/unicode_utils.py
scribe_data/unicode/update_unicode_data.py
scribe_data/unicode/cldr-annotations-derived-full/LICENSE
scribe_data/unicode/cldr-annotations-derived-full/README.md
scribe_data/unicode/cldr-annotations-derived-full/bower.json
scribe_data/unicode/cldr-annotations-derived-full/package.json
scribe_data/unicode/cldr-annotations-derived-full/annotationsDerived/af/annotations.json
scribe_data/unicode/cldr-annotations-derived-full/annotationsDerived/am/annotations.json
scribe_data/unicode/cldr-annotations-derived-full/annotationsDerived/ar/annotations.json
scribe_data/unicode/cldr-annotations-derived-full/annotationsDerived/ar-SA/annotations.json
scribe_data/unicode/cldr-annotations-derived-full/annotationsDerived/as/annotations.json
scribe_data/unicode/cldr-annotations-derived-full/annotationsDerived/ast/annotations.json
scribe_data/unicode/cldr-annotations-derived-full/annotationsDerived/az/annotations.json
scribe_data-4.1.0.dist-info/LICENSE.txt
scribe_data-4.1.0.dist-info/METADATA
scribe_data-4.1.0.dist-info/WHEEL
scribe_data-4.1.0.dist-info/entry_points.txt
scribe_data-4.1.0.dist-info/top_level.txt
scribe_data-4.1.0.dist-info/RECORD
