Metadata-Version: 2.1
Name: scribe-data
Version: 4.1.0
Summary: Wikidata and Wikipedia language data extraction
Home-page: https://github.com/scribe-org/Scribe-Data
Author: Andrew Tavis McAllister
Author-email: team@scri.be
Classifier: Development Status :: 5 - Production/Stable
Classifier: Intended Audience :: Developers
Classifier: Intended Audience :: Education
Classifier: License :: OSI Approved :: GNU General Public License v3 (GPLv3)
Classifier: Programming Language :: Python
Classifier: Programming Language :: Python :: 3
Classifier: Programming Language :: Python :: 3.9
Classifier: Programming Language :: Python :: 3.10
Classifier: Programming Language :: Python :: 3.11
Classifier: Programming Language :: Python :: 3.12
Classifier: Operating System :: OS Independent
Requires-Python: >=3.9
License-File: LICENSE.txt
Requires-Dist: beautifulsoup4==4.9.3
Requires-Dist: certifi>=2020.12.5
Requires-Dist: defusedxml==0.7.1
Requires-Dist: emoji>=2.2.0
Requires-Dist: flax>=0.8.2
Requires-Dist: iso639-lang>=2.2.3
Requires-Dist: m2r2>=0.3.3
Requires-Dist: mwparserfromhell>=0.6
Requires-Dist: numpydoc>=1.6.0
Requires-Dist: packaging>=20.9
Requires-Dist: pandas>=1.5.3
Requires-Dist: pre-commit>=3.7.1
Requires-Dist: pytest-cov>=3.0.0
Requires-Dist: questionary>=1.10.0
Requires-Dist: regex>=2023.3.23
Requires-Dist: rich>=10.0.0
Requires-Dist: ruff>=0.3.3
Requires-Dist: SPARQLWrapper>=2.0.0
Requires-Dist: sphinx-rtd-theme>=3.0.0
Requires-Dist: tqdm==4.66.4
